pymuparser/__init__.py
pymuparser/cpp/muparser_wrap.cpp
pymuparser/expression.py
pymuparser-1.1.0.dist-info/METADATA
pymuparser-1.1.0.dist-info/WHEEL
pymuparser-1.1.0.dist-info/RECORD
